opsconfig/__init__.py
opsconfig/installer.py
opsconfig/menu.py
opsconfig/nginxConfigManipulator.py
opsconfig/nginxInstaller.py
opsconfig/nginxparser.py
opsconfig/utils.py
openpdfsign_configurator-0.0.1.dist-info/LICENSE
openpdfsign_configurator-0.0.1.dist-info/METADATA
openpdfsign_configurator-0.0.1.dist-info/WHEEL
openpdfsign_configurator-0.0.1.dist-info/entry_points.txt
openpdfsign_configurator-0.0.1.dist-info/top_level.txt
openpdfsign_configurator-0.0.1.dist-info/RECORD
