Metadata-Version: 2.1
Name: openpdfsign-configurator
Version: 0.0.1
Summary: This installs open-pdf-sign as server and signs all your PDFs served with Nginx with your SSL certificate
Author-email: Thomas Schreiber <thomas@netzbeweis.com>, Philipp Omenitsch <philipp@netzbeweis.com>
License: Apache License
Project-URL: Homepage, https://github.com/open-pdf-sign/open-pdf-sign-configurator
Keywords: configurator,sign,pdf,installer
Classifier: License :: OSI Approved :: Apache Software License
Classifier: Programming Language :: Python
Classifier: Programming Language :: Python :: 3
Requires-Python: >=3.9
License-File: LICENSE
Requires-Dist: pyparsing (>=3.0.9)
Requires-Dist: PyYAML (>=6.0)
Requires-Dist: requests (>=2.28.1)
